<?xml version='1.0' encoding='utf-8'?>
<eeprom>
    <board_type addr="0" size="32">PXA1088_DKB_V1.2</board_type>
    <board_id addr="32" size="32">PXA1088_DKB_V12_23 </board_id>
    <chip_name addr="64" size="16">PXA1088</chip_name>
    <chip_stepping addr="80" size="8">A0</chip_stepping>
    <board_register_date addr="88" size="16">2/1/2014 12:09</board_register_date>
    <board_status addr="104" size="8">Good</board_status>
    <user_team addr="112" size="24">BSP Validation</user_team>
    <current_user addr="136" size="24">He Huang</current_user>
    <board_eco addr="160" size="16">ECO 14#</board_eco>
    <lcd_resolution addr="176" size="16">1080P</lcd_resolution>
    <lcd_screensize addr="192" size="8">5"</lcd_screensize>
    <ddr_type addr="200" size="8">Hynix</ddr_type>
    <ddr_size addr="208" size="8">8Gb</ddr_size>
    <emmc_type addr="216" size="8">Toshiba</emmc_type>
    <emmc_size addr="224" size="8">8Gb</emmc_size>
    <rf_name addr="232" size="8">Sparrow</rf_name>
    <rf_type addr="240" size="16">NON-LTE DSDS</rf_type>
</eeprom>
